sglearn/__init__.py
sglearn/featurization.py
sglearn-1.2.5.dist-info/AUTHORS.rst
sglearn-1.2.5.dist-info/LICENSE
sglearn-1.2.5.dist-info/METADATA
sglearn-1.2.5.dist-info/WHEEL
sglearn-1.2.5.dist-info/top_level.txt
sglearn-1.2.5.dist-info/RECORD
