Metadata-Version: 2.1
Name: sglearn
Version: 1.2.5
Summary: Python package for featurizing sgRNAs for machine learning
Home-page: https://github.com/gpp-rnd/sglearn
Author: Peter C. DeWeirdt
Author-email: petedeweirdt@gmail.com
License: MIT license
Keywords: sglearn
Platform: UNKNOWN
Classifier: Development Status :: 2 - Pre-Alpha
Classifier: Intended Audience :: Developers
Classifier: License :: OSI Approved :: MIT License
Classifier: Natural Language :: English
Classifier: Programming Language :: Python :: 3
Classifier: Programming Language :: Python :: 3.7
Classifier: Programming Language :: Python :: 3.8
Requires-Python: >=3.7
License-File: LICENSE
License-File: AUTHORS.rst
Requires-Dist: pandas (>=1.1)
Requires-Dist: biopython (>=1.77)
Requires-Dist: seqfold (>=0.7.7)
Requires-Dist: joblib (>=1.0.1)
Requires-Dist: tqdm (>=4.60.0)
